MANIFEST.in
README.md
setup.py
commlib/__init__.py
commlib/config.py
commlib/dbtool.py
commlib/encrypt.py
commlib/uplusua.py
commlib/util.py
commlib.egg-info/PKG-INFO
commlib.egg-info/SOURCES.txt
commlib.egg-info/dependency_links.txt
commlib.egg-info/requires.txt
commlib.egg-info/top_level.txt
commlib/baseutils/__init__.py
commlib/baseutils/dateutils.py
commlib/baseutils/httputils.py
commlib/baseutils/logutils.py
commlib/fabricdeploy/__init__.py
commlib/fabricdeploy/deploy.py
commlib/fabricdeploy/fs.py
commlib/fabricdeploy/git.py
commlib/fabricdeploy/helper.py
commlib/fabricdeploy/html.py
commlib/fabricdeploy/nginx.py
commlib/fabricdeploy/package.py
commlib/fabricdeploy/supervisor.py
commlib/fabricdeploy/virtualenv.py
commlib/initconfig/__init__.py
commlib/storage/__init__.py
commlib/storage/memcache/__init__.py
commlib/storage/memcache/mcPool.py
commlib/storage/mongodb/__init__.py
commlib/storage/mysql/__init__.py
commlib/storage/mysql/connPool.py
commlib/storage/redis/__init__.py
commlib/storage/redis/redisClient.py
commlib/storage/redis/redisPool.py
commlib/tools/__init__.py
commlib/tools/smartsql.py