Metadata-Version: 1.0
Name: commlib
Version: 1.0.10
Summary: common tools for develop
Home-page: https://github.com/waipbmtd/commlib
Author: Devin
Author-email: waipbmtd@gmail.com
License: GPL
Platform: UNKNOWN
